pandemic/__init__.py
pandemic/amphora.py
pandemic/city.py
pandemic/compliance.py
pandemic/conventions.py
pandemic/estimation.py
pandemic/example_parameters.py
pandemic/health.py
pandemic/main.py
pandemic/metrics.py
pandemic/movement.py
pandemic/plotting.py
pandemic/shell.py
pandemic/simulation.py
pandemic/simulator.py
pandemic/surrogate.py
pandemic/swarm.py
pandemic/util.py
pandemic/zcurves.py
pandemic-0.4.4.dist-info/METADATA
pandemic-0.4.4.dist-info/WHEEL
pandemic-0.4.4.dist-info/entry_points.txt
pandemic-0.4.4.dist-info/top_level.txt
pandemic-0.4.4.dist-info/RECORD
