Metadata-Version: 2.1
Name: pandemic
Version: 0.4.4
Summary: Orstein-Uhlenbeck pandemic simulation
Home-page: https://github.com/microprediction/pandemic
Author: microprediction
Author-email: info@microprediction.org
License: MIT
Platform: UNKNOWN
Classifier: License :: OSI Approved :: MIT License
Classifier: Programming Language :: Python :: 3
Classifier: Programming Language :: Python :: 3.7
Requires-Dist: numpy
Requires-Dist: pathlib
Requires-Dist: matplotlib
Requires-Dist: contexttimer
Requires-Dist: requests
Requires-Dist: wheel
Requires-Dist: python-geohash
Requires-Dist: deepdiff
Requires-Dist: pymorton
Requires-Dist: pytest
Requires-Dist: redis
Requires-Dist: scipy
Requires-Dist: pandas
Requires-Dist: ddeint
